std/__init__.py
mystds-0.1.dist-info/LICENCE.txt
mystds-0.1.dist-info/METADATA
mystds-0.1.dist-info/WHEEL
mystds-0.1.dist-info/top_level.txt
mystds-0.1.dist-info/RECORD
