Metadata-Version: 2.1
Name: mystds
Version: 0.1
Summary: this is my standardscaler 
Home-page: UNKNOWN
Author: Bibekananda nayak
Author-email: Bibekanandan892@gmail.com
License: UNKNOWN
Platform: UNKNOWN
Classifier: Programming Language :: Python :: 3
Classifier: License :: OSI Approved :: MIT License
Classifier: Operating System :: OS Independent
